LICENSE
MANIFEST.in
README.md
requirements.txt
setup.py
version.txt
requests_factory/__init__.py
requests_factory/__version__.py
requests_factory.egg-info/PKG-INFO
requests_factory.egg-info/SOURCES.txt
requests_factory.egg-info/dependency_links.txt
requests_factory.egg-info/requires.txt
requests_factory.egg-info/top_level.txt
test/test_requests_factory.py