Metadata-Version: 1.0
Name: requests-factory
Version: 0.1.7
Summary: HTTP Request Builder based on requests Library
Home-page: https://github.com/hsdp/requests-factory
Author: Adam Jaso
Author-email: ajaso@hsdp.io
License: 
